muffin_donald/__init__.py
muffin_donald/py.typed
muffin_donald-1.0.3.dist-info/LICENSE
muffin_donald-1.0.3.dist-info/METADATA
muffin_donald-1.0.3.dist-info/WHEEL
muffin_donald-1.0.3.dist-info/RECORD
