Metadata-Version: 2.3
Name: muffin-donald
Version: 1.0.3
Summary: It's a plugin for Muffin framework which provides support for external APIs
License: MIT
Keywords: muffin,asyncio,trio,curio
Author: Kirill Klenov
Author-email: horneds@gmail.com
Requires-Python: >=3.10,<4.0
Classifier: Development Status :: 5 - Production/Stable
Classifier: Framework :: AsyncIO
Classifier: Intended Audience :: Developers
Classifier: License :: OSI Approved :: MIT License
Classifier: Programming Language :: Python
Classifier: Programming Language :: Python :: 3
Classifier: Programming Language :: Python :: 3.10
Classifier: Programming Language :: Python :: 3.11
Classifier: Programming Language :: Python :: 3.12
Classifier: Programming Language :: Python :: 3.13
Classifier: Topic :: Internet :: WWW/HTTP
Requires-Dist: donald (>=2.0.1,<3.0.0)
Requires-Dist: muffin
Project-URL: Homepage, https://github.com/klen/muffin-donald
Project-URL: Repository, https://github.com/klen/muffin-donald
